{"slug":"property-management-firms","taxonomy":"industries","route":"/industries/property-management-firms","title":"Property Management Firm Roofing Services in Las Cruces, NM | Commercial Roofing Contractors of Las Cruces","metaDescription":"A standing roof contractor for Las Cruces property management portfolios, covering work orders, preventive maintenance, and ownership-ready reporting.","internalLinks":[{"anchor":"Roofs Built for the Santa Teresa Freight Corridor","slug":"logistics-3pl","taxonomy":"industries","href":"/industries/logistics-3pl"},{"anchor":"Roof Data for Portfolio and Acquisition Decisions","slug":"commercial-real-estate-reits","taxonomy":"industries","href":"/industries/commercial-real-estate-reits"},{"anchor":"Roofing Work Timed to the Academic Calendar","slug":"education-facilities","taxonomy":"industries","href":"/industries/education-facilities"},{"anchor":"Roofs That Handle Condensation From Both Sides","slug":"food-processing-cold-storage","taxonomy":"industries","href":"/industries/food-processing-cold-storage"},{"anchor":"A Roofing Sub That Keeps Your Schedule Moving","slug":"general-contractors","taxonomy":"industries","href":"/industries/general-contractors"},{"anchor":"Reroofing Flat and Low-Slope Buildings Across Las Cruces","slug":"commercial-reroofing","taxonomy":"services","href":"/services/commercial-reroofing"},{"anchor":"Roofing Around NMSU's University Park Footprint","slug":"university-park","taxonomy":"locations","href":"/locations/university-park"},{"anchor":"Roof Systems for Rail-Adjacent Distribution Centers Near Santa Teresa","slug":"distribution-center-roofing","taxonomy":"project-types","href":"/project-types/distribution-center-roofing"}],"html":"<h1>One Call for Every Roof in the Portfolio</h1>\n<p>Property management firms covering strip retail, small industrial, and multi-tenant office buildings across Las Cruces don't need a different roofer for every address. We work as the standing roof contact across a portfolio, so a leak call at one property and a preventive maintenance visit at another both go through the same relationship instead of starting from zero each time.</p>\n\n<h2>Work Order Response and Tenant Coordination</h2>\n<p>A roof leak call from a tenant becomes a property manager's problem the moment it's reported, and how fast that gets triaged affects the tenant relationship as much as the actual repair. We respond to work orders with a clear timeline up front — when we can get eyes on the roof, what we expect the fix to involve, and whether it's a same-visit repair or needs a follow-up. That lets the property manager give the tenant a real answer instead of \"we're looking into it.\"</p>\n<p>Multi-tenant buildings complicate access — a repair over one suite's ceiling might require notifying three tenants below the affected roof section. We coordinate that notification and access scheduling with the property manager's office rather than showing up and figuring it out on-site.</p>\n\n<h2>Preventive Maintenance Across Multiple Small Buildings</h2>\n<p>Strip retail and small commercial buildings in a management portfolio rarely get the capital attention that one large distribution center gets, which means small problems — a lifted seam, a clogged scupper, a cracked pipe boot — sit until they become leak calls. A standing maintenance visit across every property in the portfolio catches those small items before they turn into emergency repairs and unhappy tenant calls.</p>\n<p>We schedule these visits to hit before monsoon season, when the short intense downpours find every weak seam and clogged drain across a portfolio at once. Catching a clogged scupper in June costs a fraction of what a July monsoon leak claim costs once it's dripping into a tenant's ceiling tile.</p>\n\n<h2>Budget Reporting Ownership Actually Reads</h2>\n<p>Property managers answer to ownership on repair spend, and a vague invoice doesn't help that conversation. We itemize repairs by property and provide photo documentation ownership can review without a site visit, plus a running condition note on each roof so a property manager can flag which buildings are approaching a capital decision before it becomes an emergency.</p>\n<ul>\n<li>Portfolio-wide preventive maintenance scheduled ahead of monsoon season</li>\n<li>Work order response with clear repair timelines for tenant communication</li>\n<li>Photo-documented repair reporting formatted for ownership review</li>\n<li>Coordinated multi-tenant access scheduling for interior-affecting repairs</li>\n<li>Condition tracking that flags roofs approaching a capital decision</li>\n<li>Consistent contact across every property in the managed portfolio</li>\n</ul>\n<p>That condition tracking matters most at renewal or budget-planning time, when a property manager needs to walk into an ownership meeting with a defensible answer about which roofs need capital next year versus which can run another maintenance cycle.</p>\n\n<h2>Handling the Small Stuff Without a Big Invoice</h2>\n<p>A lot of property management roof calls are small — a pipe boot, a flashing seal, a debris-clogged drain — and treating every call like a major repair erodes trust with a management firm that's watching costs across dozens of buildings. We scope repairs to match the actual problem and flag when something looks like it's heading toward a bigger issue, rather than upselling every visit.</p>\n<p>That approach is what keeps a management firm calling the same roofer building after building instead of shopping every work order to the lowest bidder.</p>\n\n<h2>Turnover, Lease-Up, and Vacant-Suite Roof Checks</h2>\n<p>Tenant turnover is a natural checkpoint for a roof look. When a suite goes vacant between leases, a quick check of the roof section above it — flashing at the parapet, condition of the membrane over that bay, any signs of past patch work — costs little and catches problems before a new tenant's fixtures and inventory are sitting under a section that's about to leak.</p>\n<p>We flag these findings back to the property manager as part of the turnover process rather than a separate service call, since it's already an access window and a natural point to update the roof's condition record before the next lease starts.</p>\n\n<h2>Common Questions From Property Managers</h2>\n<h3>Can you be our standing roof contact across all our managed properties?</h3>\n<p>Yes, that's how most of our property management relationships work — one point of contact for work orders, maintenance visits, and emergency calls across every building in the portfolio.</p>\n<h3>How fast can you respond to a tenant leak complaint?</h3>\n<p>Response time depends on severity and current schedule, but we give a clear timeline on the first call so you can communicate a real answer to the tenant rather than an open-ended \"someone will look at it.\"</p>\n<h3>Do you coordinate directly with tenants or only through our office?</h3>\n<p>We work through your office for scheduling and communication unless you'd prefer direct tenant coordination — that's a preference we set up front with each management relationship.</p>\n<h3>Can you provide a single report covering every roof in our portfolio?</h3>\n<p>Yes. We track condition property by property and can compile a portfolio-wide summary for budget planning or ownership reporting whenever you need it.</p>\n<h3>What's the value of a preventive maintenance visit versus waiting for leak calls?</h3>\n<p>Catching a lifted seam or clogged drain before monsoon season costs far less than the emergency repair and tenant disruption after it's already leaking, and it extends the roof's service life across the board.</p>","image":"/images/industries/property-management-firms-commercial-roofing-contractors-las-cruces-nm.webp"}